streamlit_metrics/__init__.py
streamlit_metrics-0.1.0.dist-info/LICENSE
streamlit_metrics-0.1.0.dist-info/METADATA
streamlit_metrics-0.1.0.dist-info/WHEEL
streamlit_metrics-0.1.0.dist-info/top_level.txt
streamlit_metrics-0.1.0.dist-info/RECORD
