Metadata-Version: 2.1
Name: streamlit_metrics
Version: 0.1.0
Summary: Component for displaying important figures on a Streamlit dashboard
Home-page: https://github.com/samdobson/streamlit_metrics
Author: Sam Dobson
Author-email: 1309834+samdobson@users.noreply.github.com
License: MIT license
Keywords: streamlit
Platform: UNKNOWN
Classifier: Development Status :: 2 - Pre-Alpha
Classifier: Intended Audience :: Developers
Classifier: License :: OSI Approved :: MIT License
Classifier: Natural Language :: English
Classifier: Programming Language :: Python :: 3
Classifier: Programming Language :: Python :: 3.5
Classifier: Programming Language :: Python :: 3.6
Classifier: Programming Language :: Python :: 3.7
Classifier: Programming Language :: Python :: 3.8
Requires-Python: >=3.5
